pymitsubishi/__init__.py
pymitsubishi/__main__.py
pymitsubishi/mitsubishi_api.py
pymitsubishi/mitsubishi_controller.py
pymitsubishi/mitsubishi_parser.py
pymitsubishi-0.5.0.dist-info/licenses/LICENSE
pymitsubishi-0.5.0.dist-info/METADATA
pymitsubishi-0.5.0.dist-info/WHEEL
pymitsubishi-0.5.0.dist-info/top_level.txt
pymitsubishi-0.5.0.dist-info/RECORD
