Metadata-Version: 2.4
Name: pymitsubishi
Version: 0.5.0
Summary: Control and monitor Mitsubishi Air Conditioners
Author-email: Ashleigh Hopkins <ashleigh@example.com>
Maintainer-email: Ashleigh Hopkins <ashleigh@example.com>
License: MIT
Project-URL: Homepage, https://github.com/pymitsubishi/pymitsubishi
Project-URL: Documentation, https://github.com/pymitsubishi/pymitsubishi#readme
Project-URL: Repository, https://github.com/pymitsubishi/pymitsubishi.git
Project-URL: Issues, https://github.com/pymitsubishi/pymitsubishi/issues
Keywords: mitsubishi,aircon,air conditioner,home automation,MAC-577IF-E
Classifier: Programming Language :: Python :: 3
Classifier: Programming Language :: Python :: 3.12
Classifier: Programming Language :: Python :: 3.13
Classifier: License :: OSI Approved :: MIT License
Classifier: Operating System :: OS Independent
Classifier: Development Status :: 4 - Beta
Classifier: Intended Audience :: Developers
Classifier: Topic :: Home Automation
Classifier: Topic :: Software Development :: Libraries :: Python Modules
Requires-Python: >=3.12
License-File: LICENSE
Requires-Dist: requests
Requires-Dist: pycryptodome
Provides-Extra: dev
Requires-Dist: pytest>=7.4.0; extra == "dev"
Requires-Dist: pytest-cov>=4.1.0; extra == "dev"
Requires-Dist: pytest-asyncio>=0.21.0; extra == "dev"
Requires-Dist: mypy>=1.5.0; extra == "dev"
Requires-Dist: ruff>=0.1.0; extra == "dev"
Requires-Dist: pre-commit>=3.4.0; extra == "dev"
Requires-Dist: build>=1.0.0; extra == "dev"
Requires-Dist: twine>=4.0.0; extra == "dev"
Requires-Dist: types-requests; extra == "dev"
Dynamic: license-file
